cll/__init__.py
cll/__main__.py
cll/app.py
cll/config.py
cll/data_structs/__init__.py
cll/data_structs/data_structs.py
cll/data_structs/loom_index.py
cll/data_structs/node.py
cll/encoder.py
cll/io.py
cll/store.py
cll/templater.py
cll/tree.py
command_line_loom-0.0.8.dist-info/LICENSE
command_line_loom-0.0.8.dist-info/METADATA
command_line_loom-0.0.8.dist-info/WHEEL
command_line_loom-0.0.8.dist-info/entry_points.txt
command_line_loom-0.0.8.dist-info/RECORD
