Metadata-Version: 2.1
Name: command-line-loom
Version: 0.0.8
Summary: 
Home-page: https://github.com/fergusfettes/command-line-loom
Author: fergus
Author-email: fergusfettes@gmail.com
Requires-Python: >=3.8.1,<3.12
Classifier: Programming Language :: Python :: 3
Classifier: Programming Language :: Python :: 3.9
Classifier: Programming Language :: Python :: 3.10
Classifier: Programming Language :: Python :: 3.11
Requires-Dist: click (>=8.1.3,<9.0.0)
Requires-Dist: click-shell (>=2.1,<3.0)
Requires-Dist: iterfzf (>=0.5.0.20.0,<0.6.0.0.0)
Requires-Dist: llama-index (>=0.6.8,<0.7.0)
Requires-Dist: networkx (>=3.1,<4.0)
Requires-Dist: openai (>=0.27.0,<0.28.0)
Requires-Dist: python-dotenv (>=1.0.0,<2.0.0)
Requires-Dist: pyyaml (>=6.0,<7.0)
Requires-Dist: rich (>=13.3.5,<14.0.0)
Requires-Dist: tiktoken (>=0.3.0,<0.4.0)
Requires-Dist: turbo-text-transformer-prompts (>=0.1.10,<0.2.0)
Requires-Dist: typer (>=0.9.0,<0.10.0)
Requires-Dist: typer-shell (>=0.1.6,<0.2.0)
